transcribe_anything/__init__.py
transcribe_anything/_cmd.py
transcribe_anything/api.py
transcribe_anything/audio.py
transcribe_anything/cuda_available.py
transcribe_anything/generate_speaker_json.py
transcribe_anything/insanely_fast_whisper.py
transcribe_anything/insanley_fast_whisper_reqs.py
transcribe_anything/install_whisper.py
transcribe_anything/logger.py
transcribe_anything/parse_whisper_options.py
transcribe_anything/srt_translation.py
transcribe_anything/srt_wrap.py
transcribe_anything/util.py
transcribe_anything/whisper.py
transcribe_anything/ytldp_download.py
jusScribe-0.0.1.dist-info/LICENSE
jusScribe-0.0.1.dist-info/METADATA
jusScribe-0.0.1.dist-info/WHEEL
jusScribe-0.0.1.dist-info/entry_points.txt
jusScribe-0.0.1.dist-info/top_level.txt
jusScribe-0.0.1.dist-info/RECORD
