Metadata-Version: 2.1
Name: jusScribe
Version: 0.0.1
Summary: Uses whisper AI to transcribe speach from video and audio files. Also accepts urls for youtube, rumble, bitchute, clear file, etc.
Home-page: https://github.com/S1LV4/jusScribe
Author: S1LV4
Author-email: dont@email.me
License: MIT
Keywords: transcription translation speech-to-text speech-recognition command-line-tool ai whisper ml anything
Classifier: License :: OSI Approved :: MIT License
Classifier: Environment :: Console
Classifier: Programming Language :: Python :: 3.9
Classifier: Operating System :: Microsoft :: Windows
Classifier: Operating System :: POSIX
Classifier: Operating System :: MacOS :: MacOS X
Classifier: Environment :: Console
Requires-Python: >=3.10.0
License-File: LICENSE
Requires-Dist: static-ffmpeg>=2.7
Requires-Dist: yt-dlp>=2023.3.4
Requires-Dist: appdirs==1.4.4
Requires-Dist: disklru>=1.0.7
Requires-Dist: isolated-environment~=1.3.4
Requires-Dist: FileLock
Requires-Dist: webvtt-py==0.4.6
